{
    "appid": 1071900,
    "name": "后遗症／Sequela",
    "type": "Game",
    "schinese_name": "",
    "isfreeapp": 1,
    "update_time": "2025-07-15 22:32:52",
    "change_number": 30077500,
    "depot": {
        "baselanguages": "schinese",
        "1071901": {
            "manifests": {
                "public": {
                    "gid": "1536848052180016147",
                    "size": "233146458",
                    "download": "101989136"
                }
            },
            "decryptionkey": "ac58d66f2f955f8fbb02b8403546c0b92266a8546f2f7f3623da11d9188e348c"
        },
        "branches": {
            "public": {
                "buildid": "4697628",
                "timeupdated": "1582222314"
            }
        }
    }
}