{
    "appid": 1195230,
    "name": "Darkness and Flame: Enemy in Reflection",
    "type": "Game",
    "schinese_name": "",
    "isfreeapp": 0,
    "update_time": "2025-06-23 12:13:49",
    "change_number": 29437814,
    "depot": {
        "228988": {
            "config": {
                "oslist": "windows"
            },
            "depotfromapp": "228980",
            "sharedinstall": "1"
        },
        "baselanguages": "english,german,french,italian,koreana,spanish,russian,japanese,polish,dutch,czech,brazilian,ukrainian",
        "1195231": {
            "manifests": {
                "public": {
                    "gid": "4514057949832253033",
                    "size": "1467065361",
                    "download": "1457273472"
                }
            },
            "decryptionkey": "eba1127da94ba537b6808f7213b01451793620fcdc7b28273a2c92ae9f0fb07d"
        },
        "1195232": {
            "config": {
                "oslist": "windows",
                "osarch": "32"
            },
            "manifests": {
                "public": {
                    "gid": "3480962157757469833",
                    "size": "1470556769",
                    "download": "1460796816"
                }
            },
            "decryptionkey": "d0a8e3f7be0973ad8bdb4cae99017af05d716e8e75484c99aa62f2282fd148d7"
        },
        "1195233": {
            "config": {
                "oslist": "windows",
                "osarch": "64"
            },
            "manifests": {
                "public": {
                    "gid": "6073631325680023323",
                    "size": "1471750217",
                    "download": "1461162864"
                }
            },
            "decryptionkey": "67b733e76de4c8749a6dc7746b0d37b6aff827296a32014533feb6c7012d94e8"
        },
        "branches": {
            "public": {
                "buildid": "8587987",
                "timeupdated": "1650530305"
            }
        },
        "privatebranches": "1"
    }
}