{
    "appid": 1247000,
    "name": "Lords Of The Fallen Soundtrack (2014)",
    "type": "Music",
    "schinese_name": "",
    "isfreeapp": 0,
    "update_time": "2025-06-23 09:39:47",
    "change_number": 26201212,
    "depot": {
        "1247001": {
            "config": {
                "highqualityaudio": "1",
                "language": ""
            },
            "manifests": {
                "public": {
                    "gid": "1644029612000800841",
                    "size": "580628120",
                    "download": "502459296"
                }
            },
            "decryptionkey": "2e3949549f50a5654bd1456bf521e122ff26b570dd440a6ea3c6c12b7cda89e6"
        },
        "1247002": {
            "config": {
                "language": ""
            },
            "manifests": {
                "public": {
                    "gid": "8441249760443778968",
                    "size": "73936885",
                    "download": "73869296"
                }
            },
            "decryptionkey": "c52f94303d06cdbe4980c50c792eba0d00c9acec6ca70f94f387c57dbfbc0daf"
        },
        "branches": {
            "public": {
                "buildid": "4667620",
                "timeupdated": "1581499177"
            }
        }
    }
}