{
    "appid": 1277920,
    "name": "Ethyrial, Echoes of Yore",
    "type": "Game",
    "schinese_name": "谜岛: 旧日的回响",
    "isfreeapp": 1,
    "update_time": "2025-07-17 09:35:03",
    "change_number": 30106195,
    "depot": {
        "229006": {
            "config": {
                "oslist": "windows"
            },
            "depotfromapp": "228980",
            "sharedinstall": "1"
        },
        "229007": {
            "config": {
                "oslist": "windows"
            },
            "depotfromapp": "228980",
            "sharedinstall": "1"
        },
        "hasdepotsindlc": "0",
        "baselanguages": "english",
        "1277921": {
            "config": {
                "oslist": "windows"
            },
            "manifests": {
                "public": {
                    "gid": "5479828209218196552",
                    "size": "27893199486",
                    "download": "13949057600"
                }
            },
            "decryptionkey": "790b6c474987a4fe21cf4cf59190895088e279bdddc16684754161de6570d029"
        },
        "1277922": {
            "config": {
                "oslist": "macos"
            },
            "manifests": {
                "public": {
                    "gid": "3246272739338096837",
                    "size": "26967700746",
                    "download": "13489570912"
                }
            },
            "decryptionkey": "ed3758f9d6d3dabb6744f49e487ed73cb44ffe184940d5f2f81da92135671908"
        },
        "1277923": {
            "config": {
                "oslist": "linux"
            },
            "manifests": {
                "public": {
                    "gid": "1087466191372758930",
                    "size": "28095351005",
                    "download": "14155166544"
                }
            },
            "decryptionkey": "358927525cdf508134741940919975d9747082ce0c8fab43ff65ff79cb7c4a36"
        },
        "branches": {
            "public": {
                "buildid": "19244003",
                "timeupdated": "1752665512"
            }
        }
    }
}