{
    "appid": 1302570,
    "name": "Vampirem",
    "type": "Game",
    "schinese_name": "",
    "isfreeapp": 0,
    "update_time": "2025-06-23 11:23:23",
    "change_number": 29528768,
    "depot": {
        "228990": {
            "config": {
                "oslist": "windows"
            },
            "depotfromapp": "228980",
            "sharedinstall": "1"
        },
        "1302571": {
            "manifests": {
                "public": {
                    "gid": "5028491020459154166",
                    "size": "18628104154",
                    "download": "6677685856"
                }
            },
            "decryptionkey": "2731bf0e61e2d8fe389c1bff0b5d0e4f4d9aa11b77ed96d23147fd9d8a559c3d"
        },
        "branches": {
            "public": {
                "buildid": "8196474",
                "timeupdated": "1644793812"
            }
        }
    }
}