{
    "appid": 1336430,
    "name": "Waves of Rotting Flesh",
    "type": "Game",
    "schinese_name": "",
    "isfreeapp": 0,
    "update_time": "2025-07-10 00:01:16",
    "change_number": 29977337,
    "depot": {
        "1336431": {
            "manifests": {
                "public": {
                    "gid": "6712615228555724949",
                    "size": "362272543",
                    "download": "206767184"
                }
            },
            "decryptionkey": "968fa3bbc29c11bc8a896996a40b53f27be7141c5f2fe0baaeb420a93905c934"
        },
        "branches": {
            "public": {
                "buildid": "5257780",
                "timeupdated": "1594073584"
            }
        }
    }
}