{
    "appid": 1401340,
    "name": "Tea Garden Simulator",
    "type": "Game",
    "schinese_name": "",
    "isfreeapp": 0,
    "update_time": "2025-07-20 19:51:31",
    "change_number": 30156950,
    "depot": {
        "1401341": {
            "config": {
                "language": "english",
                "oslist": "windows"
            },
            "manifests": {
                "public": {
                    "gid": "8112076789542614908",
                    "size": "871098182",
                    "download": "138930800"
                }
            },
            "decryptionkey": "f4d28332e199c9cd7e4836a89f5065632083696bcc98e5615c218f6f33097339"
        },
        "branches": {
            "public": {
                "buildid": "16026971",
                "timeupdated": "1728831881"
            }
        },
        "privatebranches": "1"
    }
}