{
    "appid": 1463600,
    "name": "RPG Maker MZ - RE-D FINAL BATTLE MUSIC PACK",
    "type": "DLC",
    "schinese_name": "",
    "isfreeapp": 0,
    "update_time": "2025-06-30 19:59:12",
    "change_number": 26201212,
    "depot": {
        "1463600": {
            "config": {
                "language": ""
            },
            "manifests": {
                "public": {
                    "gid": "3042309385564409177",
                    "size": "548262397",
                    "download": "510195792"
                }
            },
            "dlcappid": "1463600",
            "decryptionkey": "1c5d08062c4482375af1db0113ab0f64d3c87ccb3216f6f84ff3c9648fa28524"
        },
        "branches": {
            "public": {
                "buildid": "5769786",
                "timeupdated": "1604284585"
            }
        }
    }
}