{
    "appid": 1490340,
    "name": "We Are OFK",
    "type": "Game",
    "schinese_name": "",
    "isfreeapp": 0,
    "update_time": "2025-07-14 07:11:09",
    "change_number": 30043092,
    "depot": {
        "1490343": {
            "config": {
                "oslist": "windows",
                "osarch": "64"
            },
            "manifests": {
                "public": {
                    "gid": "7533459417384558247",
                    "size": "246",
                    "download": "240"
                }
            },
            "decryptionkey": "d72b3113b5e909f8a410e385f25df9b0d5a1e702e60b250ff8f59efaff267dfd"
        },
        "1490344": {
            "config": {
                "oslist": "macos",
                "osarch": "64"
            }
        },
        "1490348": {
            "config": {
                "oslist": "windows",
                "osarch": "64"
            }
        },
        "1490349": {
            "config": {
                "oslist": "macos",
                "osarch": "64"
            }
        },
        "1490345": {
            "config": {
                "oslist": "macos"
            },
            "manifests": {
                "public": {
                    "gid": "4798669884788494075",
                    "size": "14841668702",
                    "download": "2137660784"
                }
            },
            "decryptionkey": "b0237aae3dad057759ec3180ff4b4281b8a808e6189d2aff1310340e412acda8"
        },
        "1490346": {
            "config": {
                "oslist": "windows"
            },
            "manifests": {
                "public": {
                    "gid": "2862538450066239971",
                    "size": "14841942498",
                    "download": "2137780128"
                }
            },
            "decryptionkey": "2c9fd2b749a4e7438ffaac2b09d369bd2de97e158df994abb424eb259a38fc7e"
        },
        "branches": {
            "public": {
                "buildid": "9474660",
                "timeupdated": "1662622465"
            }
        },
        "privatebranches": "1"
    }
}