{
    "appid": 1544150,
    "name": "HarmonEy",
    "type": "Game",
    "schinese_name": "",
    "isfreeapp": 0,
    "update_time": "2025-07-10 20:35:44",
    "change_number": 29996103,
    "depot": {
        "baselanguages": "english,japanese",
        "228990": {
            "config": {
                "oslist": "windows"
            },
            "depotfromapp": "228980",
            "sharedinstall": "1"
        },
        "1544151": {
            "config": {
                "oslist": "windows"
            },
            "manifests": {
                "public": {
                    "gid": "6018552317364763551",
                    "size": "1239034172",
                    "download": "1072330048"
                }
            },
            "decryptionkey": "50978d42b00f02eca89a2dc7172e964e8129a76afb354def2019620e3247527b"
        },
        "branches": {
            "public": {
                "buildid": "6263320",
                "timeupdated": "1613721325"
            }
        }
    }
}