{
    "appid": 1857080,
    "name": "The Last Starship",
    "type": "Game",
    "schinese_name": "",
    "isfreeapp": 0,
    "update_time": "2025-07-03 15:55:15",
    "change_number": 29881009,
    "depot": {
        "1857081": {},
        "1857082": {
            "config": {
                "oslist": "windows"
            },
            "manifests": {
                "public": {
                    "gid": "8812287459377254926",
                    "size": "842569291",
                    "download": "838835776"
                },
                "hotfix_test": {
                    "gid": "4721353115483972327",
                    "size": "833885992",
                    "download": "829813920"
                }
            },
            "decryptionkey": "da7ba42e5dc0fab717beb28a4fbae2ec0da3e4805937202e20fd4ada15520b16"
        },
        "1857083": {
            "config": {
                "oslist": "macos"
            },
            "manifests": {
                "public": {
                    "gid": "212752304560191637",
                    "size": "849970188",
                    "download": "840864992"
                },
                "hotfix_test": {
                    "gid": "8015964696483471650",
                    "size": "841096837",
                    "download": "831424832"
                }
            },
            "decryptionkey": "d31765f2383e42a54b6614804aa4f36915de4b8d6615fdcdcfce3f873f158f82"
        },
        "workshopdepot": "1857080",
        "branches": {
            "public": {
                "buildid": "18965433",
                "timeupdated": "1750771877"
            },
            "hotfix_test": {
                "buildid": "18754948",
                "description": "Hotfix Public Testing",
                "timeupdated": "1749147599"
            }
        },
        "privatebranches": "1",
        "workshopdepotdecryptionkey": "83b0560e7dd05cd8c6f1c190b12c52b9c79ee662bc1a087f6b495244c6fbc6b8"
    }
}