{
    "appid": 1926660,
    "name": "OUTLANDER",
    "type": "Game",
    "schinese_name": "",
    "isfreeapp": 1,
    "update_time": "2025-07-09 11:09:37",
    "change_number": 29966075,
    "depot": {
        "1926661": {
            "manifests": {
                "public": {
                    "gid": "8462047682653083523",
                    "size": "209038357",
                    "download": "51485408"
                }
            },
            "decryptionkey": "06732ef27ebdcc4150eb5dce38f77cb2ceeea7a17cfaf534f2b84e39352d3234"
        },
        "branches": {
            "public": {
                "buildid": "19158730",
                "timeupdated": "1752055772"
            }
        }
    }
}