{
    "appid": 2203780,
    "name": "Alien",
    "type": "Game",
    "schinese_name": "外星人",
    "isfreeapp": 0,
    "update_time": "2025-07-16 15:35:51",
    "change_number": 30091384,
    "depot": {
        "2203781": {
            "manifests": {
                "public": {
                    "gid": "3409383530401411405",
                    "size": "395460755",
                    "download": "289608576"
                }
            },
            "decryptionkey": "e845b9067f449b83656ecde2e033ad4f82d339393fbba6ac0b48675b942ad65d"
        },
        "branches": {
            "public": {
                "buildid": "9845246",
                "timeupdated": "1667311038"
            }
        }
    }
}