{
    "appid": 2302670,
    "name": "Back to Vietnam",
    "type": "Game",
    "schinese_name": "重返越南",
    "isfreeapp": 0,
    "update_time": "2025-07-19 15:24:24",
    "change_number": 30146994,
    "depot": {
        "228988": {
            "config": {
                "oslist": "windows"
            },
            "depotfromapp": "228980",
            "sharedinstall": "1"
        },
        "228990": {
            "config": {
                "oslist": "windows"
            },
            "depotfromapp": "228980",
            "sharedinstall": "1"
        },
        "229000": {
            "config": {
                "oslist": "windows"
            },
            "depotfromapp": "228980",
            "sharedinstall": "1"
        },
        "2302671": {
            "manifests": {
                "public": {
                    "gid": "1530190551378175429",
                    "size": "5544091660",
                    "download": "4338820544"
                }
            },
            "decryptionkey": "43cd5065e5cd157ce5400ea4c54f98eb92631ff3a9146515f810232cbaa8952a"
        },
        "baselanguages": "english,schinese",
        "branches": {
            "public": {
                "buildid": "19285864",
                "timeupdated": "1752935060"
            }
        }
    }
}