{
    "appid": 2346510,
    "name": "Rainbowcore Hypernova",
    "type": "Game",
    "schinese_name": "",
    "isfreeapp": 1,
    "update_time": "2025-07-13 20:12:33",
    "change_number": 30038154,
    "depot": {
        "2346511": {
            "manifests": {
                "public": {
                    "gid": "1015795251494790529",
                    "size": "2207272623",
                    "download": "186110720"
                }
            },
            "decryptionkey": "1a06726d02fa8d45a70529e18732fe1004fbf605066ce8c3429724f2cada6881"
        },
        "baselanguages": "english",
        "branches": {
            "public": {
                "buildid": "11168775",
                "timeupdated": "1683334433"
            }
        }
    }
}