{
    "appid": 2536650,
    "name": "TYPECAST",
    "type": "Game",
    "schinese_name": "",
    "isfreeapp": 0,
    "update_time": "2025-07-22 01:20:42",
    "change_number": 30176714,
    "depot": {
        "2536651": {
            "config": {
                "oslist": "windows"
            },
            "manifests": {
                "public": {
                    "gid": "8467543384144584417",
                    "size": "257488307",
                    "download": "204749216"
                }
            },
            "decryptionkey": "3e512226e99dbf990fa0e750d9764eaee6c1ecd9e80149fbfdfaffb2ced009b3"
        },
        "branches": {
            "public": {
                "buildid": "16763669",
                "timeupdated": "1734381427"
            }
        },
        "privatebranches": "1"
    }
}