{
    "appid": 2644490,
    "name": "Archery Showdown",
    "type": "Game",
    "schinese_name": "",
    "isfreeapp": 1,
    "update_time": "2025-06-23 05:17:54",
    "change_number": 29696945,
    "depot": {
        "baselanguages": "english",
        "2644491": {
            "config": {
                "oslist": "windows",
                "osarch": "64",
                "language": "english"
            },
            "manifests": {
                "public": {
                    "gid": "410630791126871619",
                    "size": "27538602",
                    "download": "15348048"
                }
            },
            "decryptionkey": "088ea45db6a9ce55aecd4d9a025c6477ff0eba6c6aa5f8e0d8c120fd0922693f"
        },
        "branches": {
            "public": {
                "buildid": "12628599",
                "timeupdated": "1699266634"
            }
        }
    }
}