{
    "appid": 2680190,
    "name": "Rails Across America",
    "type": "Game",
    "schinese_name": "",
    "isfreeapp": 0,
    "update_time": "2025-06-23 11:16:54",
    "change_number": 29544520,
    "depot": {
        "2680191": {
            "manifests": {
                "public": {
                    "gid": "1642756500998696025",
                    "size": "328071615",
                    "download": "199195392"
                }
            },
            "decryptionkey": "dc834751cf19a28e7da79694a4302831f9c53b97433fa4d417092c6c6f0936a0"
        },
        "2680192": {
            "config": {
                "language": "russian"
            },
            "manifests": {
                "public": {
                    "gid": "4475993366904802118",
                    "size": "154646301",
                    "download": "40713920"
                }
            },
            "decryptionkey": "0e985e48f115d9bb4d8cf11c87032fdaaefb5e3c27db4e1a62030aafd3624c57"
        },
        "branches": {
            "public": {
                "buildid": "17437756",
                "timeupdated": "1740049757"
            }
        },
        "privatebranches": "1"
    }
}