{
    "appid": 2791010,
    "name": "ProtectHeart",
    "type": "Game",
    "schinese_name": "",
    "isfreeapp": 1,
    "update_time": "2025-07-20 02:51:39",
    "change_number": 30151162,
    "depot": {
        "2791011": {
            "manifests": {
                "public": {
                    "gid": "3761936742966243814",
                    "size": "85250975",
                    "download": "26671920"
                }
            },
            "decryptionkey": "b3f2101ef821654552cab3b87142df9618204692f9dc240230ae06c6065d0af0"
        },
        "branches": {
            "public": {
                "buildid": "13729114",
                "timeupdated": "1710348194"
            }
        }
    }
}