{
    "appid": 2829060,
    "name": "COMPUTER FURY",
    "type": "Game",
    "schinese_name": "",
    "isfreeapp": 0,
    "update_time": "2025-06-23 13:07:35",
    "change_number": 29311839,
    "depot": {
        "baselanguages": "english",
        "hasdepotsindlc": "0",
        "2829061": {
            "config": {
                "language": "english",
                "oslist": "windows"
            },
            "manifests": {
                "public": {
                    "gid": "5988823439974789818",
                    "size": "1271513076",
                    "download": "214408880"
                }
            },
            "decryptionkey": "00791d0ea17073b83dbc6e3751a8c9409c43c30663ee604dab72d257ffccdde2"
        },
        "branches": {
            "public": {
                "buildid": "18692830",
                "timeupdated": "1748790048"
            }
        }
    }
}