{
    "appid": 3104970,
    "name": "Backyard Baseball '01",
    "type": "Game",
    "schinese_name": "",
    "isfreeapp": 0,
    "update_time": "2025-07-23 18:56:04",
    "change_number": 30212111,
    "depot": {
        "228989": {
            "config": {
                "oslist": "windows"
            },
            "depotfromapp": "228980",
            "sharedinstall": "1"
        },
        "3104971": {
            "manifests": {
                "public": {
                    "gid": "6252278961538232351",
                    "size": "358506829",
                    "download": "173094720"
                }
            },
            "decryptionkey": "756d390df697e201eab2f90d0f9ed46dd7f9cbde188e0be0eb31f3b437639e7a"
        },
        "branches": {
            "public": {
                "buildid": "19150897",
                "timeupdated": "1752004504"
            }
        },
        "privatebranches": "1"
    }
}