{
    "appid": 3148790,
    "name": "MiSa",
    "type": "Game",
    "schinese_name": "",
    "isfreeapp": 0,
    "update_time": "2025-06-25 07:03:02",
    "change_number": 29711104,
    "depot": {
        "3148791": {
            "manifests": {
                "public": {
                    "gid": "1748512085352240411",
                    "size": "1306616195",
                    "download": "414998432"
                }
            },
            "decryptionkey": "d48e599a8ab05b9bf76d9919f9b859fadd8d7660feb4d3a161fb08d1a62d673a"
        },
        "baselanguages": "english",
        "branches": {
            "public": {
                "buildid": "17082746",
                "timeupdated": "1737493524"
            }
        }
    }
}