{
    "appid": 3242870,
    "name": "Pushmania",
    "type": "Game",
    "schinese_name": "",
    "isfreeapp": 0,
    "update_time": "2025-07-22 22:14:20",
    "change_number": 30194188,
    "depot": {
        "baselanguages": "english,czech",
        "3242871": {
            "config": {
                "oslist": "windows",
                "osarch": "64"
            },
            "manifests": {
                "public": {
                    "gid": "636046445806503273",
                    "size": "489387937",
                    "download": "362986592"
                }
            },
            "decryptionkey": "cf249cb0bbba7d51782283029f0abe0dde052b455e17b2c7ec583cc7f5dbafa0"
        },
        "workshopdepot": "3242870",
        "branches": {
            "public": {
                "buildid": "19320269",
                "timeupdated": "1753218855"
            }
        },
        "privatebranches": "1",
        "workshopdepotdecryptionkey": ""
    }
}