{
    "appid": 3260890,
    "name": "iVRy GearVR System Files Installer",
    "type": "DLC",
    "schinese_name": "",
    "isfreeapp": 1,
    "update_time": "2025-06-23 10:42:31",
    "change_number": 26629927,
    "depot": {
        "3260891": {
            "manifests": {
                "public": {
                    "gid": "7019320513901799080",
                    "size": "380533410",
                    "download": "385254176"
                }
            },
            "dlcappid": "3260890",
            "decryptionkey": "037629a2f44a4420d209aa927eea9b9108f40afc02190b31e062beb2961a53fd"
        },
        "branches": {
            "public": {
                "buildid": "16735652",
                "timeupdated": "1734095511"
            }
        }
    }
}