{
    "appid": 334370,
    "name": "From Earth",
    "type": "Game",
    "schinese_name": "",
    "isfreeapp": 1,
    "update_time": "2025-07-10 10:00:14",
    "change_number": 29984587,
    "depot": {
        "334371": {
            "config": {
                "oslist": "windows"
            },
            "manifests": {
                "public": {
                    "gid": "1546363560613794630",
                    "size": "5581060556",
                    "download": "2742072400"
                }
            },
            "decryptionkey": "4433242192361dceb3511d13aeec557c20a2535dbebeace22603c792692c3c84"
        },
        "branches": {
            "public": {
                "buildid": "3037755",
                "timeupdated": "1534421332"
            }
        }
    }
}