{
    "appid": 3427170,
    "name": "マスターオブモンスターズSSB",
    "type": "Game",
    "schinese_name": "",
    "isfreeapp": 0,
    "update_time": "2025-07-04 10:35:46",
    "change_number": 29894874,
    "depot": {
        "3427171": {
            "config": {
                "oslist": "windows"
            },
            "manifests": {
                "public": {
                    "gid": "2850176588196653934",
                    "size": "1391022367",
                    "download": "493810848"
                },
                "version_1.0.2": {
                    "gid": "297852220686220990",
                    "size": "1402638080",
                    "download": "501436800"
                },
                "version_1.0.3": {
                    "gid": "2913897897678533997",
                    "size": "1358465714",
                    "download": "457311088"
                },
                "version_1.0.4": {
                    "gid": "5735048090189145027",
                    "size": "1393475251",
                    "download": "491352368"
                }
            },
            "decryptionkey": "3d24c924006dcd10d4a0490c965f6892a46d44ab050a2712f0c328b78b7d8596"
        },
        "3759570": {
            "dlcappid": "3759570",
            "config": {
                "oslist": "windows"
            },
            "manifests": {
                "public": {
                    "gid": "8437752212359997577",
                    "size": "32218458",
                    "download": "24130816"
                },
                "version_1.0.2": {
                    "gid": "8437752212359997577",
                    "size": "32218458",
                    "download": "24130816"
                },
                "version_1.0.3": {
                    "gid": "8437752212359997577",
                    "size": "32218458",
                    "download": "24130816"
                },
                "version_1.0.4": {
                    "gid": "8437752212359997577",
                    "size": "32218458",
                    "download": "24130816"
                }
            },
            "decryptionkey": "3a150128f82e062b8bae66f0023efb0132e8754548cbec0fa9c3d908170785e2"
        },
        "branches": {
            "public": {
                "buildid": "19106035",
                "timeupdated": "1751621726"
            },
            "version_1.0.2": {
                "buildid": "18988351",
                "description": "Previous version",
                "timeupdated": "1751017684"
            },
            "version_1.0.3": {
                "buildid": "19023924",
                "description": "Previous version",
                "timeupdated": "1751362183"
            },
            "version_1.0.4": {
                "buildid": "19062920",
                "description": "Previous version",
                "timeupdated": "1751621739"
            }
        },
        "privatebranches": "1"
    }
}