{
    "appid": 3777060,
    "name": "Gold Miner:Classic Edition",
    "type": "Game",
    "schinese_name": "黄金矿工:经典版",
    "isfreeapp": 0,
    "update_time": "2025-07-23 14:15:26",
    "change_number": 30206952,
    "depot": {
        "228989": {
            "config": {
                "oslist": "windows"
            },
            "depotfromapp": "228980",
            "sharedinstall": "1"
        },
        "228990": {
            "config": {
                "oslist": "windows"
            },
            "depotfromapp": "228980",
            "sharedinstall": "1"
        },
        "3777061": {
            "manifests": {
                "public": {
                    "gid": "7025319357816772623",
                    "size": "398692828",
                    "download": "260236832"
                }
            },
            "decryptionkey": "dd1f55a4e091d904244cdd3d10c8f77d867475716419896c4e53be1afbce421e"
        },
        "branches": {
            "public": {
                "buildid": "19274323",
                "timeupdated": "1752839730"
            }
        },
        "privatebranches": "1"
    }
}