{
    "appid": 3822960,
    "name": "Zekertune",
    "type": "Game",
    "schinese_name": "",
    "isfreeapp": 0,
    "update_time": "2025-07-15 15:08:49",
    "change_number": 30069981,
    "depot": {
        "3822961": {
            "manifests": {
                "public": {
                    "gid": "6248369756010945762",
                    "size": "2401830792",
                    "download": "1540138560"
                }
            },
            "decryptionkey": "435adaa5bd02866c57f48b171a4189efd678a16e721dfbdf8da8fad2c1acee98"
        },
        "branches": {
            "public": {
                "buildid": "19230961",
                "timeupdated": "1752588522"
            }
        }
    }
}