{
    "appid": 458430,
    "name": "Steel Seed",
    "type": "Game",
    "schinese_name": "钢铁之种",
    "isfreeapp": 0,
    "update_time": "2025-07-22 15:43:02",
    "change_number": 30188192,
    "depot": {
        "baselanguages": "english",
        "228989": {
            "config": {
                "oslist": "windows"
            },
            "depotfromapp": "228980",
            "sharedinstall": "1"
        },
        "228990": {
            "config": {
                "oslist": "windows"
            },
            "depotfromapp": "228980",
            "sharedinstall": "1"
        },
        "458432": {
            "config": {
                "oslist": "windows"
            },
            "manifests": {
                "public": {
                    "gid": "5904060916341964624",
                    "size": "40705517583",
                    "download": "29592868736"
                }
            },
            "decryptionkey": "676d0c262af24e6cd734932d053a9997f4e69a5226ac436b337b04054884257a"
        },
        "3626520": {
            "dlcappid": "3626520",
            "manifests": {
                "public": {
                    "gid": "4513624616451772644",
                    "size": "861518154",
                    "download": "861942112"
                }
            },
            "decryptionkey": "9e6ccdec2df7d0d334069f38327098dd7fad54e37fc15d75f364187201721c2d"
        },
        "branches": {
            "public": {
                "buildid": "18882597",
                "timeupdated": "1752244072"
            }
        },
        "privatebranches": "1"
    }
}