{
    "appid": 513330,
    "name": "Party Hard Tycoon",
    "type": "Game",
    "schinese_name": "",
    "isfreeapp": 0,
    "update_time": "2025-07-05 12:10:00",
    "change_number": 29909767,
    "depot": {
        "hasdepotsindlc": "1",
        "513331": {
            "config": {
                "oslist": "windows",
                "language": ""
            },
            "manifests": {
                "public": {
                    "gid": "8501852131379500816",
                    "size": "543848102",
                    "download": "138252960"
                }
            },
            "decryptionkey": "240f1a6dac9a9b632fea85d69dd0623719104ece2273824c02da16176f144b3e"
        },
        "branches": {
            "public": {
                "buildid": "3606907",
                "timeupdated": "1551436591"
            }
        },
        "privatebranches": "1"
    }
}