{
    "appid": 581980,
    "name": "Candy Machine",
    "type": "Game",
    "schinese_name": "",
    "isfreeapp": 0,
    "update_time": "2025-07-07 02:11:10",
    "change_number": 29923153,
    "depot": {
        "581981": {
            "manifests": {
                "public": {
                    "gid": "2581253015588373702",
                    "size": "232659334",
                    "download": "52288320"
                }
            },
            "decryptionkey": "94aa6f6fa7e0f5a3b59a9a88833e87e2f427f78e71f1e224a73fce21822a51b7"
        },
        "branches": {
            "public": {
                "buildid": "1777696",
                "timeupdated": "1493053791"
            }
        }
    }
}