{
    "appid": 673900,
    "name": "Avem33",
    "type": "Game",
    "schinese_name": "",
    "isfreeapp": 1,
    "update_time": "2025-06-27 14:16:00",
    "change_number": 29787528,
    "depot": {
        "673901": {
            "config": {
                "oslist": "windows"
            },
            "manifests": {
                "public": {
                    "gid": "8651282326786338207",
                    "size": "118184952",
                    "download": "42289920"
                }
            },
            "decryptionkey": "68f9655013d320e7a24380d31473598dad3ff1be5b0ce8d72d165b5bf0010db2"
        },
        "branches": {
            "public": {
                "buildid": "1941290",
                "timeupdated": "1499350656"
            }
        }
    }
}