{
    "appid": 681720,
    "name": "BoxMaker",
    "type": "Game",
    "schinese_name": "",
    "isfreeapp": 0,
    "update_time": "2025-07-23 21:11:55",
    "change_number": 30214030,
    "depot": {
        "681721": {
            "config": {
                "oslist": "windows"
            },
            "manifests": {
                "public": {
                    "gid": "7047306963854693018",
                    "size": "146301315",
                    "download": "36580288"
                }
            },
            "decryptionkey": "ce11d9c19c54df8a1b8a785990a7cbd746b939532d5dfaf9e25e424836b4859c"
        },
        "branches": {
            "public": {
                "buildid": "1965988",
                "timeupdated": "1500283418"
            }
        }
    }
}